connector/__init__.py
connector/core/__init__.py
connector/core/manifest/__init__.py
connector/core/manifest/api.py
connector/core/manifest/base.py
connector/core/manifest/generator.py
connector/core/openapi_translator/__init__.py
connector/core/openapi_translator/base_translator.py
connector/core/openapi_translator/registry_integration.py
connector/core/registry/__init__.py
connector/core/registry/auto_discovery.py
connector/core/registry/service_registry.py
connector/core/resource.py
connector/core/run_configuration.py
connector/core/service.py
connector/core/strategies/__init__.py
connector/core/strategies/auth/__init__.py
connector/core/strategies/auth/base_auth.py
connector/core/strategies/auth/basic_auth.py
connector/core/strategies/auth/oauth2_auth.py
connector/core/strategies/auth/token_auth.py
connector/core/strategies/pagination/__init__.py
connector/core/strategies/pagination/base_pagination.py
connector/core/strategies/pagination/cursor_pagination.py
connector/core/strategies/pagination/offset_pagination.py
connector/core/strategies/retry/__init__.py
connector/core/strategies/retry/base_retry.py
connector/core/strategies/retry/exponential_backoff.py
connector/core/strategies/retry/linear_backoff.py
connector/services/__init__.py
connector/services/adform.py
connector/services/airbyte.py
connector/services/asana_client.py
connector/services/base_resource.py
connector/services/base_service.py
connector/services/baselinker_api.py
connector/services/bigquery.py
connector/services/bq_gsheet_upload.py
connector/services/budgetbakers_wallet.py
connector/services/clockify.py
connector/services/cube.py
connector/services/drive_service.py
connector/services/ecomail.py
connector/services/email_client.py
connector/services/email_ext.py
connector/services/email_extract.py
connector/services/email_messages.py
connector/services/fakturoid.py
connector/services/fio.py
connector/services/firestore.py
connector/services/gcalendar.md
connector/services/gcs_client.py
datamancers_etl_toolbox-0.1.dist-info/LICENSE
datamancers_etl_toolbox-0.1.dist-info/METADATA
datamancers_etl_toolbox-0.1.dist-info/WHEEL
datamancers_etl_toolbox-0.1.dist-info/RECORD
