Metadata-Version: 2.1
Name: datamancers-etl-toolbox
Version: 0.1
Summary: ETL toolkit for data processing and transformation
License: MIT
Keywords: etl,data-processing,kestra,cloud-functions
Author: vitmrnavek
Author-email: vit.mrnavek@datamancers.cz
Requires-Python: >=3.10,<4.0
Classifier: License :: OSI Approved :: MIT License
Classifier: Programming Language :: Python :: 3
Classifier: Programming Language :: Python :: 3.10
Classifier: Programming Language :: Python :: 3.11
Classifier: Programming Language :: Python :: 3.12
Provides-Extra: ai
Provides-Extra: all
Provides-Extra: all-services
Provides-Extra: all-transformers
Provides-Extra: asana
Provides-Extra: audio
Provides-Extra: bigquery
Provides-Extra: calendar
Provides-Extra: duckdb
Provides-Extra: firestore
Provides-Extra: gcs
Provides-Extra: google-sheets
Provides-Extra: jupyter
Provides-Extra: mcp
Provides-Extra: mssql
Provides-Extra: pdf
Provides-Extra: places
Provides-Extra: translate
Provides-Extra: xml-builder
Provides-Extra: xml-to-csv
Requires-Dist: db-dtypes (>=1.0.0,<2.0.0) ; extra == "bigquery" or extra == "all-services" or extra == "all"
Requires-Dist: duckdb (>=1.1.3,<2.0.0) ; extra == "duckdb" or extra == "all"
Requires-Dist: fastmcp (>=0.1.0,<0.2.0) ; extra == "mcp" or extra == "all-services" or extra == "all"
Requires-Dist: ffmpeg-python (>=0.2.0,<0.3.0) ; extra == "audio" or extra == "all"
Requires-Dist: gcsa (>=2.0,<3.0) ; extra == "calendar" or extra == "all-services" or extra == "all"
Requires-Dist: google-api-python-client (>=2.0.0,<3.0.0) ; extra == "google-sheets" or extra == "mcp" or extra == "all-services" or extra == "all"
Requires-Dist: google-auth (>=2.0.0,<3.0.0) ; extra == "google-sheets" or extra == "mcp" or extra == "all-services" or extra == "all"
Requires-Dist: google-auth-httplib2 (>=0.2.0,<0.3.0) ; extra == "google-sheets" or extra == "mcp" or extra == "all-services" or extra == "all"
Requires-Dist: google-cloud-aiplatform (>=1.97.0,<2.0.0) ; extra == "translate" or extra == "all-transformers" or extra == "all"
Requires-Dist: google-cloud-bigquery (>=3.34.0,<4.0.0) ; extra == "bigquery" or extra == "all-services" or extra == "all"
Requires-Dist: google-cloud-firestore (>=2.21.0,<3.0.0) ; extra == "firestore" or extra == "all-services" or extra == "all"
Requires-Dist: google-cloud-storage (>=2.13.0,<3.0.0) ; extra == "gcs" or extra == "translate" or extra == "all-services" or extra == "all-transformers" or extra == "all"
Requires-Dist: google-cloud-translate (>=3.0.0,<4.0.0) ; extra == "translate" or extra == "all-transformers" or extra == "all"
Requires-Dist: google-maps-places (>=0.2.2,<0.3.0) ; extra == "places" or extra == "all-services" or extra == "all"
Requires-Dist: httpx (>=0.27.0,<0.28.0) ; extra == "calendar" or extra == "all-services" or extra == "all"
Requires-Dist: importlib-resources (>=5.0.0,<6.0.0)
Requires-Dist: ipykernel (>=6.30.1,<7.0.0) ; extra == "jupyter" or extra == "all"
Requires-Dist: jsonpointer (>=3.0.0,<4.0.0)
Requires-Dist: langchain (>=0.3.25,<0.4.0) ; extra == "ai" or extra == "all"
Requires-Dist: langchain-google-genai (>=2.1.4,<3.0.0) ; extra == "ai" or extra == "all"
Requires-Dist: langsmith (>=0.1.0,<0.2.0) ; extra == "ai" or extra == "all"
Requires-Dist: lxml (>=4.9.3,<5.0.0) ; extra == "xml-to-csv" or extra == "xml-builder" or extra == "all-transformers" or extra == "all"
Requires-Dist: nbconvert (>=7.1.0,<8.0.0) ; extra == "jupyter" or extra == "all"
Requires-Dist: nbformat (>=5.10.0,<6.0.0) ; extra == "jupyter" or extra == "all"
Requires-Dist: openai (>=1.65.0,<2.0.0) ; extra == "audio" or extra == "all"
Requires-Dist: pdf2image (>=1.17.0,<2.0.0) ; extra == "pdf" or extra == "all"
Requires-Dist: pydantic (>=2.0.0,<3.0.0)
Requires-Dist: pydub (>=0.25.1,<0.26.0) ; extra == "audio" or extra == "all"
Requires-Dist: pygsheets (>=2.0.6,<3.0.0) ; extra == "google-sheets" or extra == "mcp" or extra == "all-services" or extra == "all"
Requires-Dist: pyodbc (>=5.1.0,<6.0.0) ; extra == "mssql" or extra == "all-services" or extra == "all"
Requires-Dist: python-dotenv (>=1.0.1,<2.0.0)
Requires-Dist: python-multipart (>=0.0.9,<0.0.10)
Requires-Dist: pytz (>=2025.2,<2026.0) ; extra == "calendar" or extra == "all-services" or extra == "all"
Requires-Dist: pyyaml (>=6.0.1,<7.0.0)
Requires-Dist: requests (>=2.31.0,<3.0.0)
Requires-Dist: tenacity (>=8.2.0,<9.0.0) ; extra == "translate" or extra == "all-transformers" or extra == "all"
